README.rst
setup.py
esp/__init__.py
esp/alert.py
esp/auth.py
esp/cloud_trail_event.py
esp/compliance_control.py
esp/contact_request.py
esp/created_by.py
esp/credential.py
esp/custom_signature.py
esp/dashboard.py
esp/disabled_signature.py
esp/external_account.py
esp/metadata.py
esp/organization.py
esp/region.py
esp/report.py
esp/resource.py
esp/scan_interval.py
esp/sdk.py
esp/service.py
esp/settings.py
esp/signature.py
esp/stat.py
esp/stat_custom_signature.py
esp/stat_region.py
esp/stat_service.py
esp/stat_signature.py
esp/sub_organization.py
esp/suppression.py
esp/tag.py
esp/team.py
esp/user.py
esp/utilities.py
esp.egg-info/PKG-INFO
esp.egg-info/SOURCES.txt
esp.egg-info/dependency_links.txt
esp.egg-info/requires.txt
esp.egg-info/top_level.txt
esp/packages/__init__.py
esp/packages/six.py
esp/packages/requests/__init__.py
esp/packages/requests/adapters.py
esp/packages/requests/api.py
esp/packages/requests/auth.py
esp/packages/requests/cacert.pem
esp/packages/requests/certs.py
esp/packages/requests/compat.py
esp/packages/requests/cookies.py
esp/packages/requests/exceptions.py
esp/packages/requests/hooks.py
esp/packages/requests/models.py
esp/packages/requests/sessions.py
esp/packages/requests/status_codes.py
esp/packages/requests/structures.py
esp/packages/requests/utils.py
esp/packages/requests/packages/__init__.py
esp/packages/requests/packages/chardet/__init__.py
esp/packages/requests/packages/chardet/big5freq.py
esp/packages/requests/packages/chardet/big5prober.py
esp/packages/requests/packages/chardet/chardetect.py
esp/packages/requests/packages/chardet/chardistribution.py
esp/packages/requests/packages/chardet/charsetgroupprober.py
esp/packages/requests/packages/chardet/charsetprober.py
esp/packages/requests/packages/chardet/codingstatemachine.py
esp/packages/requests/packages/chardet/compat.py
esp/packages/requests/packages/chardet/constants.py
esp/packages/requests/packages/chardet/cp949prober.py
esp/packages/requests/packages/chardet/escprober.py
esp/packages/requests/packages/chardet/escsm.py
esp/packages/requests/packages/chardet/eucjpprober.py
