Metadata-Version: 1.1
Name: esp
Version: 0.1.8
Summary: Evident Security Platform (ESP) SDK for Python
Home-page: UNKNOWN
Author: John Hutchison
Author-email: hutch@evident.io
License: UNKNOWN
Platform: UNKNOWN
Classifier: Development Status :: 5 - Production/Stable
Classifier: Intended Audience :: Developers
Classifier: Natural Language :: English
Classifier: Programming Language :: Python
Classifier: Programming Language :: Python :: 2.7
Classifier: Programming Language :: Python :: 3
Classifier: Programming Language :: Python :: 3.4
Classifier: Programming Language :: Python :: 3.5
Classifier: Programming Language :: Python :: Implementation :: CPython
